data_processing/__init__.py
data_processing/calculate_tool.py
data_processing/frequency.py
data_processing/to_fixed.py
data_processing-0.1.3.dist-info/METADATA
data_processing-0.1.3.dist-info/WHEEL
data_processing-0.1.3.dist-info/top_level.txt
data_processing-0.1.3.dist-info/RECORD
