Metadata-Version: 2.1
Name: data-processing
Version: 0.1.3
Summary: Data Processing Tools. :)
Home-page: https://gitee.com/whimlin/publish_project.git
Author: shlinn
Author-email: shlinn@foxmail.com
License: UNKNOWN
Platform: UNKNOWN
